{"classes":["EQUIPMENT","SIZE","CAPACITY","POWER","FUEL_TYPE","LOA","TYPE","FLOWRATE"],"annotations":[["Backflow Preventer\r",{"entities":[[0,18,"EQUIPMENT"]]}],["Backflow Preventer - 1\" pipe\r",{"entities":[[0,18,"EQUIPMENT"],[21,23,"SIZE"]]}],["Backflow Preventer - 1.5\" pipe\r",{"entities":[[0,18,"EQUIPMENT"],[21,25,"SIZE"]]}],["Backflow Preventer - 2\" pipe\r",{"entities":[[0,18,"EQUIPMENT"],[21,23,"SIZE"]]}],["Backflow Preventer - 3\" pipe\r",{"entities":[[0,18,"EQUIPMENT"],[21,23,"SIZE"]]}],["Backflow Preventer - 4\" pipe\r",{"entities":[[0,18,"EQUIPMENT"],[21,23,"SIZE"]]}],["Backflow Preventer - 6\" pipe\r",{"entities":[[0,18,"EQUIPMENT"],[21,23,"SIZE"]]}],["Backflow Preventer - 8\" pipe\r",{"entities":[[0,18,"EQUIPMENT"],[21,23,"SIZE"]]}],["Booster Pump\r",{"entities":[[0,12,"EQUIPMENT"]]}],["Booster Pump - <1 HP\r",{"entities":[[0,12,"EQUIPMENT"],[15,20,"POWER"]]}],["Booster Pump - 1 HP\r",{"entities":[[0,12,"EQUIPMENT"],[15,19,"POWER"]]}],["Booster Pump - 1.5 HP\r",{"entities":[[0,12,"EQUIPMENT"],[15,21,"POWER"]]}],["Booster Pump - 10 HP\r",{"entities":[[0,12,"EQUIPMENT"],[15,20,"POWER"]]}],["Booster Pump - 2 HP\r",{"entities":[[0,12,"EQUIPMENT"],[15,19,"POWER"]]}],["Booster Pump - 3 HP\r",{"entities":[[0,12,"EQUIPMENT"],[15,19,"POWER"]]}],["Booster Pump - 5 HP\r",{"entities":[[0,12,"EQUIPMENT"],[15,19,"POWER"]]}],["Booster Pump - 7.5 HP\r",{"entities":[[0,12,"EQUIPMENT"],[15,21,"POWER"]]}],["Booster Pump - Variable speed, 15 HP, 6\" discharge, 1000 GPM\r",{"entities":[[0,12,"EQUIPMENT"],[15,29,"TYPE"],[31,36,"POWER"],[38,40,"SIZE"],[52,60,"FLOWRATE"]]}],["Booster Pump - Variable speed, 30 HP, 6\" discharge, 1700 GPM\r",{"entities":[[0,12,"EQUIPMENT"],[15,29,"TYPE"],[31,36,"POWER"],[38,40,"SIZE"],[52,60,"FLOWRATE"]]}],["Booster Pump - Variable speed, 7.5 HP, 4\" discharge, 400 GPM\r",{"entities":[[0,12,"EQUIPMENT"],[15,29,"TYPE"],[31,37,"POWER"],[39,41,"SIZE"],[53,60,"FLOWRATE"]]}],["Heat Transfer Package - One pump system,  28 GPM\r",{"entities":[[0,21,"EQUIPMENT"],[24,39,"TYPE"],[42,48,"FLOWRATE"]]}],["Heat Transfer Package - One pump system,  35 GPM\r",{"entities":[[0,21,"EQUIPMENT"],[24,39,"TYPE"],[42,48,"FLOWRATE"]]}],["Heat Transfer Package - One pump system,  55 GPM\r",{"entities":[[0,21,"EQUIPMENT"],[24,39,"TYPE"],[42,48,"FLOWRATE"]]}],["Heat Transfer Package - One pump system, 130 GPM\r",{"entities":[[0,21,"EQUIPMENT"],[24,39,"TYPE"],[41,48,"FLOWRATE"]]}],["Heat Transfer Package - One pump system, 255 GPM\r",{"entities":[[0,21,"EQUIPMENT"],[24,39,"TYPE"],[41,48,"FLOWRATE"]]}],["Heat Transfer Package - One pump system, 550 GPM\r",{"entities":[[0,21,"EQUIPMENT"],[24,39,"TYPE"],[41,48,"FLOWRATE"]]}],["Heat Transfer Package - One pump system, 800 GPM\r",{"entities":[[0,21,"EQUIPMENT"],[24,39,"TYPE"],[41,48,"FLOWRATE"]]}],["Heat Transfer Package - Two pump system, 130 GPM\r",{"entities":[[0,21,"EQUIPMENT"],[24,39,"TYPE"],[41,48,"FLOWRATE"]]}],["Heat Transfer Package - Two pump system, 255 GPM\r",{"entities":[[0,21,"EQUIPMENT"],[24,39,"TYPE"],[41,48,"FLOWRATE"]]}],["Heat Transfer Package - Two pump system, 28 GPM\r",{"entities":[[0,21,"EQUIPMENT"],[24,39,"TYPE"],[41,47,"FLOWRATE"]]}],["Heat Transfer Package - Two pump system, 35 GPM\r",{"entities":[[0,21,"EQUIPMENT"],[24,39,"TYPE"],[41,47,"FLOWRATE"]]}],["Heat Transfer Package - Two pump system, 55 GPM\r",{"entities":[[0,21,"EQUIPMENT"],[24,39,"TYPE"],[41,47,"FLOWRATE"]]}],["Heat Transfer Package - Two pump system, 550 GPM\r",{"entities":[[0,21,"EQUIPMENT"],[24,39,"TYPE"],[41,48,"FLOWRATE"]]}],["Heat Transfer Package - Two pump system, 800 GPM\r",{"entities":[[0,21,"EQUIPMENT"],[24,39,"TYPE"],[41,48,"FLOWRATE"]]}],["Storage Tank\r",{"entities":[[0,12,"EQUIPMENT"]]}],["Storage Tank - Galvanized steel, 135 gallon, 24\" diameter, 75\" L.O.A.\r",{"entities":[[0,12,"EQUIPMENT"],[15,31,"TYPE"],[33,43,"CAPACITY"],[45,48,"SIZE"],[59,68,"LOA"]]}],["Storage Tank - Galvanized steel, 15 gallon, 14\" diameter, 26\" L.O.A.\r",{"entities":[[0,12,"EQUIPMENT"],[15,31,"TYPE"],[33,42,"CAPACITY"],[44,47,"SIZE"],[58,67,"LOA"]]}],["Storage Tank - Galvanized steel, 240 gallon, 30\" diameter, 86\" L.O.A.\r",{"entities":[[0,12,"EQUIPMENT"],[15,31,"TYPE"],[33,43,"CAPACITY"],[45,48,"SIZE"],[59,68,"LOA"]]}],["Storage Tank - Galvanized steel, 30 gallon, 14\" diameter, 49\" L.O.A.\r",{"entities":[[0,12,"EQUIPMENT"],[15,31,"TYPE"],[33,42,"CAPACITY"],[44,47,"SIZE"],[58,67,"LOA"]]}],["Storage Tank - Galvanized steel, 300 gallon, 36\" diameter, 76\" L.O.A.\r",{"entities":[[0,12,"EQUIPMENT"],[15,31,"TYPE"],[33,43,"CAPACITY"],[45,48,"SIZE"],[59,68,"LOA"]]}],["Storage Tank - Galvanized steel, 400 gallon, 36\" diameter, 100\" L.O.A.\r",{"entities":[[0,12,"EQUIPMENT"],[15,31,"TYPE"],[33,43,"CAPACITY"],[45,48,"SIZE"],[59,69,"LOA"]]}],["Storage Tank - Galvanized steel, 500 gallon, 36\" diameter,126\" L.O.A.\r",{"entities":[[0,12,"EQUIPMENT"],[15,31,"TYPE"],[33,43,"CAPACITY"],[45,48,"SIZE"],[58,68,"LOA"]]}],["Storage Tank - Galvanized steel, 80 gallon, 20\" diameter, 64\" L.O.A.\r",{"entities":[[0,12,"EQUIPMENT"],[15,31,"TYPE"],[33,42,"CAPACITY"],[44,47,"SIZE"],[58,67,"LOA"]]}],["Storage Tank - Glass lined, PE, 1330 gallon, 66\" diameter, 107\" L.O.A.\r",{"entities":[[0,12,"EQUIPMENT"],[15,30,"TYPE"],[32,43,"CAPACITY"],[45,48,"SIZE"],[59,69,"LOA"]]}],["Storage Tank - Glass lined, PE, 140 gallon, 24\" diameter, 80\" L.O.A.\r",{"entities":[[0,12,"EQUIPMENT"],[15,30,"TYPE"],[32,42,"CAPACITY"],[44,47,"SIZE"],[58,67,"LOA"]]}],["Storage Tank - Glass lined, PE, 1615 gallon, 72\" diameter, 110\" L.O.A.\r",{"entities":[[0,12,"EQUIPMENT"],[15,30,"TYPE"],[32,43,"CAPACITY"],[45,48,"SIZE"],[59,69,"LOA"]]}],["Storage Tank - Glass lined, PE, 225 gallon, 30\" diameter, 78\" L.O.A.\r",{"entities":[[0,12,"EQUIPMENT"],[15,30,"TYPE"],[32,42,"CAPACITY"],[44,47,"SIZE"],[58,67,"LOA"]]}],["Storage Tank - Glass lined, PE, 2285 gallon, 84\" diameter, 128\" L.O.A.\r",{"entities":[[0,12,"EQUIPMENT"],[15,30,"TYPE"],[32,43,"CAPACITY"],[45,48,"SIZE"],[59,69,"LOA"]]}],["Storage Tank - Glass lined, PE, 325 gallon, 36\" diameter, 81\" L.O.A.\r",{"entities":[[0,12,"EQUIPMENT"],[15,30,"TYPE"],[32,42,"CAPACITY"],[44,47,"SIZE"],[58,67,"LOA"]]}],["Storage Tank - Glass lined, PE, 3440 gallon, 96\" diameter, 157\" L.O.A.\r",{"entities":[[0,12,"EQUIPMENT"],[15,30,"TYPE"],[32,43,"CAPACITY"],[45,48,"SIZE"],[59,69,"LOA"]]}],["Storage Tank - Glass lined, PE, 460 gallon, 42\" diameter, 84\" L.O.A.\r",{"entities":[[0,12,"EQUIPMENT"],[15,30,"TYPE"],[32,42,"CAPACITY"],[44,47,"SIZE"],[58,67,"LOA"]]}],["Storage Tank - Glass lined, PE, 605 gallon, 48\" diameter, 87\" L.O.A.\r",{"entities":[[0,12,"EQUIPMENT"],[15,30,"TYPE"],[32,42,"CAPACITY"],[44,47,"SIZE"],[58,67,"LOA"]]}],["Storage Tank - Glass lined, PE, 740 gallon, 54\" diameter, 91\" L.O.A.\r",{"entities":[[0,12,"EQUIPMENT"],[15,30,"TYPE"],[32,42,"CAPACITY"],[44,47,"SIZE"],[58,67,"LOA"]]}],["Storage Tank - Glass lined, PE, 80 gallon, 20\" diameter, 64\" L.O.A.\r",{"entities":[[0,12,"EQUIPMENT"],[15,30,"TYPE"],[32,41,"CAPACITY"],[43,46,"SIZE"],[57,66,"LOA"]]}],["Storage Tank - Glass lined, PE, 940 gallon, 60\" diameter, 93\" L.O.A.\r",{"entities":[[0,12,"EQUIPMENT"],[15,30,"TYPE"],[32,42,"CAPACITY"],[44,47,"SIZE"],[58,67,"LOA"]]}],["Tankless Heater - Electric\r",{"entities":[[0,15,"EQUIPMENT"],[18,26,"FUEL_TYPE"]]}],["Tankless Heater - Gas",{"entities":[[0,15,"EQUIPMENT"],[18,21,"FUEL_TYPE"]]}],["Water Heaters, Commercial, Electric\r",{"entities":[[0,13,"EQUIPMENT"],[15,25,"TYPE"],[27,35,"FUEL_TYPE"]]}],["Water Heaters, Commercial, Electric -   50 gal,    9 KW,   37 GPH\r",{"entities":[[0,13,"EQUIPMENT"],[15,25,"TYPE"],[27,35,"FUEL_TYPE"],[40,46,"CAPACITY"],[51,55,"POWER"],[59,65,"FLOWRATE"]]}],["Water Heaters, Commercial, Electric -   80 gal,   12 KW,   49 GPH\r",{"entities":[[0,13,"EQUIPMENT"],[15,25,"TYPE"],[27,35,"FUEL_TYPE"],[40,46,"CAPACITY"],[50,55,"POWER"],[59,65,"FLOWRATE"]]}],["Water Heaters, Commercial, Electric -   80 gal,   36 KW,  147 GPH\r",{"entities":[[0,13,"EQUIPMENT"],[15,25,"TYPE"],[27,35,"FUEL_TYPE"],[40,46,"CAPACITY"],[50,55,"POWER"],[58,65,"FLOWRATE"]]}],["Water Heaters, Commercial, Electric -  120 gal,  36 KW,  147 GPH\r",{"entities":[[0,13,"EQUIPMENT"],[15,25,"TYPE"],[27,35,"FUEL_TYPE"],[39,46,"CAPACITY"],[49,54,"POWER"],[57,64,"FLOWRATE"]]}],["Water Heaters, Commercial, Electric -  150 gal, 120 KW,  490 GPH\r",{"entities":[[0,13,"EQUIPMENT"],[15,25,"TYPE"],[27,35,"FUEL_TYPE"],[39,46,"CAPACITY"],[48,54,"POWER"],[57,64,"FLOWRATE"]]}],["Water Heaters, Commercial, Electric -  200 gal, 120 KW,  490 GPH\r",{"entities":[[0,13,"EQUIPMENT"],[15,25,"TYPE"],[27,35,"FUEL_TYPE"],[39,46,"CAPACITY"],[48,54,"POWER"],[57,64,"FLOWRATE"]]}],["Water Heaters, Commercial, Electric -  250 gal, 150 KW,  615 GPH\r",{"entities":[[0,13,"EQUIPMENT"],[15,25,"TYPE"],[27,35,"FUEL_TYPE"],[39,46,"CAPACITY"],[48,54,"POWER"],[57,64,"FLOWRATE"]]}],["Water Heaters, Commercial, Electric -  300 gal, 180 KW,  738 GPH\r",{"entities":[[0,13,"EQUIPMENT"],[15,25,"TYPE"],[27,35,"FUEL_TYPE"],[39,46,"CAPACITY"],[48,54,"POWER"],[57,64,"FLOWRATE"]]}],["Water Heaters, Commercial, Electric -  350 gal,   30 KW,  123 GPH\r",{"entities":[[0,13,"EQUIPMENT"],[15,25,"TYPE"],[27,35,"FUEL_TYPE"],[39,46,"CAPACITY"],[50,55,"POWER"],[58,65,"FLOWRATE"]]}],["Water Heaters, Commercial, Electric -  350 gal, 180 KW,  738 GPH\r",{"entities":[[0,13,"EQUIPMENT"],[15,25,"TYPE"],[27,35,"FUEL_TYPE"],[39,46,"CAPACITY"],[48,54,"POWER"],[57,64,"FLOWRATE"]]}],["Water Heaters, Commercial, Electric -  500 gal,   30 KW,  123 GPH\r",{"entities":[[0,13,"EQUIPMENT"],[15,25,"TYPE"],[27,35,"FUEL_TYPE"],[39,46,"CAPACITY"],[50,55,"POWER"],[58,65,"FLOWRATE"]]}],["Water Heaters, Commercial, Electric -  500 gal, 240 KW,  984 GPH\r",{"entities":[[0,13,"EQUIPMENT"],[15,25,"TYPE"],[27,35,"FUEL_TYPE"],[39,46,"CAPACITY"],[48,54,"POWER"],[57,64,"FLOWRATE"]]}],["Water Heaters, Commercial, Electric -  700 gal,   30 KW,  123 GPH\r",{"entities":[[0,13,"EQUIPMENT"],[15,25,"TYPE"],[27,35,"FUEL_TYPE"],[39,46,"CAPACITY"],[50,55,"POWER"],[58,65,"FLOWRATE"]]}],["Water Heaters, Commercial, Electric -  700 gal, 300 KW, 1230 GPH\r",{"entities":[[0,13,"EQUIPMENT"],[15,25,"TYPE"],[27,35,"FUEL_TYPE"],[39,46,"CAPACITY"],[48,54,"POWER"],[56,64,"FLOWRATE"]]}],["Water Heaters, Commercial, Electric - 1000 gal,   60 KW,  245 GPH\r",{"entities":[[0,13,"EQUIPMENT"],[15,25,"TYPE"],[27,35,"FUEL_TYPE"],[38,46,"CAPACITY"],[50,55,"POWER"],[58,65,"FLOWRATE"]]}],["Water Heaters, Commercial, Electric - 1000 gal, 480 KW, 1970 GPH\r",{"entities":[[0,13,"EQUIPMENT"],[15,25,"TYPE"],[27,35,"FUEL_TYPE"],[38,46,"CAPACITY"],[48,54,"POWER"],[56,64,"FLOWRATE"]]}],["Water Heaters, Commercial, Electric - 1500 gal,   60 KW,  245 GPH\r",{"entities":[[0,13,"EQUIPMENT"],[15,25,"TYPE"],[27,35,"FUEL_TYPE"],[38,46,"CAPACITY"],[50,55,"POWER"],[58,65,"FLOWRATE"]]}],["Water Heaters, Commercial, Electric - 1500 gal, 480 KW, 1970 GPH\r",{"entities":[[0,13,"EQUIPMENT"],[15,25,"TYPE"],[27,35,"FUEL_TYPE"],[38,46,"CAPACITY"],[48,54,"POWER"],[56,64,"FLOWRATE"]]}],["Water Heaters, Commercial, Gas\r",{"entities":[[0,13,"EQUIPMENT"],[15,25,"TYPE"],[27,30,"FUEL_TYPE"]]}],["Water Heaters, Commercial, Gas -  75 MBH input,  63 GPH\r",{"entities":[[0,13,"EQUIPMENT"],[15,25,"TYPE"],[27,30,"FUEL_TYPE"],[34,46,"POWER"],[49,55,"FLOWRATE"]]}],["Water Heaters, Commercial, Gas -  95 MBH input,  86 GPH\r",{"entities":[[0,13,"EQUIPMENT"],[15,25,"TYPE"],[27,30,"FUEL_TYPE"],[34,46,"POWER"],[49,55,"FLOWRATE"]]}],["Water Heaters, Commercial, Gas - 100 MBH input,  91 GPH\r",{"entities":[[0,13,"EQUIPMENT"],[15,25,"TYPE"],[27,30,"FUEL_TYPE"],[33,46,"POWER"],[49,55,"FLOWRATE"]]}],["Water Heaters, Commercial, Gas - 115 MBH input, 110 GPH\r",{"entities":[[0,13,"EQUIPMENT"],[15,25,"TYPE"],[27,30,"FUEL_TYPE"],[33,46,"POWER"],[48,55,"FLOWRATE"]]}],["Water Heaters, Commercial, Gas - 155 MBH input, 150 GPH\r",{"entities":[[0,13,"EQUIPMENT"],[15,25,"TYPE"],[27,30,"FUEL_TYPE"],[33,46,"POWER"],[48,55,"FLOWRATE"]]}],["Water Heaters, Commercial, Gas - 175 MBH input, 168 GPH\r",{"entities":[[0,13,"EQUIPMENT"],[15,25,"TYPE"],[27,30,"FUEL_TYPE"],[33,46,"POWER"],[48,55,"FLOWRATE"]]}],["Water Heaters, Commercial, Gas - 200 MBH input, 192 GPH\r",{"entities":[[0,13,"EQUIPMENT"],[15,25,"TYPE"],[27,30,"FUEL_TYPE"],[33,46,"POWER"],[48,55,"FLOWRATE"]]}],["Water Heaters, Commercial, Gas - 240 MBH input, 230 GPH\r",{"entities":[[0,13,"EQUIPMENT"],[15,25,"TYPE"],[27,30,"FUEL_TYPE"],[33,46,"POWER"],[48,55,"FLOWRATE"]]}],["Water Heaters, Commercial, Gas - 300 MBH input, 278 GPH\r",{"entities":[[0,13,"EQUIPMENT"],[15,25,"TYPE"],[27,30,"FUEL_TYPE"],[33,46,"POWER"],[48,55,"FLOWRATE"]]}],["Water Heaters, Commercial, Gas - 390 MBH input, 374 GPH\r",{"entities":[[0,13,"EQUIPMENT"],[15,25,"TYPE"],[27,30,"FUEL_TYPE"],[33,46,"POWER"],[48,55,"FLOWRATE"]]}],["Water Heaters, Commercial, Gas - 500 MBH input, 480 GPH\r",{"entities":[[0,13,"EQUIPMENT"],[15,25,"TYPE"],[27,30,"FUEL_TYPE"],[33,46,"POWER"],[48,55,"FLOWRATE"]]}],["Water Heaters, Commercial, Gas - 600 MBH input, 576 GPH\r",{"entities":[[0,13,"EQUIPMENT"],[15,25,"TYPE"],[27,30,"FUEL_TYPE"],[33,46,"POWER"],[48,55,"FLOWRATE"]]}],["Water Heaters, Commercial, Oil\r",{"entities":[[0,13,"EQUIPMENT"],[15,25,"TYPE"],[27,30,"FUEL_TYPE"]]}],["Water Heaters, Commercial, Oil - 140 gal,  140 MBH input,  134 GPH\r",{"entities":[[0,13,"EQUIPMENT"],[15,25,"TYPE"],[27,30,"FUEL_TYPE"],[33,40,"CAPACITY"],[43,56,"POWER"],[59,66,"FLOWRATE"]]}],["Water Heaters, Commercial, Oil - 140 gal,  255 MBH input,  247 GPH\r",{"entities":[[0,13,"EQUIPMENT"],[15,25,"TYPE"],[27,30,"FUEL_TYPE"],[33,40,"CAPACITY"],[43,56,"POWER"],[59,66,"FLOWRATE"]]}],["Water Heaters, Commercial, Oil - 140 gal,  270 MBH input,  259 GPH\r",{"entities":[[0,13,"EQUIPMENT"],[15,25,"TYPE"],[27,30,"FUEL_TYPE"],[33,40,"CAPACITY"],[43,56,"POWER"],[59,66,"FLOWRATE"]]}],["Water Heaters, Commercial, Oil - 140 gal,  400 MBH input,  384 GPH\r",{"entities":[[0,13,"EQUIPMENT"],[15,25,"TYPE"],[27,30,"FUEL_TYPE"],[33,40,"CAPACITY"],[43,56,"POWER"],[59,66,"FLOWRATE"]]}],["Water Heaters, Commercial, Oil - 140 gal,  720 MBH input,  691 GPH\r",{"entities":[[0,13,"EQUIPMENT"],[15,25,"TYPE"],[27,30,"FUEL_TYPE"],[33,40,"CAPACITY"],[43,56,"POWER"],[59,66,"FLOWRATE"]]}],["Water Heaters, Commercial, Oil - 201 gal, 1000 MBH input,  960 GPH\r",{"entities":[[0,13,"EQUIPMENT"],[15,25,"TYPE"],[27,30,"FUEL_TYPE"],[33,40,"CAPACITY"],[42,56,"POWER"],[59,66,"FLOWRATE"]]}],["Water Heaters, Commercial, Oil - 201 gal, 1250 MBH input, 1200 GPH\r",{"entities":[[0,13,"EQUIPMENT"],[15,25,"TYPE"],[27,30,"FUEL_TYPE"],[33,40,"CAPACITY"],[42,56,"POWER"],[58,66,"FLOWRATE"]]}],["Water Heaters, Commercial, Oil - 201 gal, 1500 MBH input, 1441 GPH\r",{"entities":[[0,13,"EQUIPMENT"],[15,25,"TYPE"],[27,30,"FUEL_TYPE"],[33,40,"CAPACITY"],[42,56,"POWER"],[58,66,"FLOWRATE"]]}],["Water Heaters, Commercial, Oil - 221 gal,  300 MBH input,  288 GPH\r",{"entities":[[0,13,"EQUIPMENT"],[15,25,"TYPE"],[27,30,"FUEL_TYPE"],[33,40,"CAPACITY"],[43,56,"POWER"],[59,66,"FLOWRATE"]]}],["Water Heaters, Commercial, Oil - 221 gal,  600 MBH input,  576 GPH\r",{"entities":[[0,13,"EQUIPMENT"],[15,25,"TYPE"],[27,30,"FUEL_TYPE"],[33,40,"CAPACITY"],[43,56,"POWER"],[59,66,"FLOWRATE"]]}],["Water Heaters, Commercial, Oil - 221 gal,  800 MBH input,  768 GPH\r",{"entities":[[0,13,"EQUIPMENT"],[15,25,"TYPE"],[27,30,"FUEL_TYPE"],[33,40,"CAPACITY"],[43,56,"POWER"],[59,66,"FLOWRATE"]]}],["Water Heaters, Commercial, Oil - 397 gal, 1500 MBH input, 1441 GPH\r",{"entities":[[0,13,"EQUIPMENT"],[15,25,"TYPE"],[27,30,"FUEL_TYPE"],[33,40,"CAPACITY"],[42,56,"POWER"],[58,66,"FLOWRATE"]]}],["Water Heaters, Commercial, Oil - 397 gal, 1750 MBH input, 1681 GPH\r",{"entities":[[0,13,"EQUIPMENT"],[15,25,"TYPE"],[27,30,"FUEL_TYPE"],[33,40,"CAPACITY"],[42,56,"POWER"],[58,66,"FLOWRATE"]]}],["Water Heaters, Commercial, Oil - 411 gal,  600 MBH input,   576 GPH\r",{"entities":[[0,13,"EQUIPMENT"],[15,25,"TYPE"],[27,30,"FUEL_TYPE"],[33,40,"CAPACITY"],[43,56,"POWER"],[60,67,"FLOWRATE"]]}],["Water Heaters, Commercial, Oil - 411 gal,  800 MBH input,   768 GPH\r",{"entities":[[0,13,"EQUIPMENT"],[15,25,"TYPE"],[27,32,"FUEL_TYPE"],[33,40,"CAPACITY"],[43,56,"POWER"],[60,67,"FLOWRATE"]]}],["Water Heaters, Commercial, Oil - 411 gal, 1000 MBH input,  960 GPH\r",{"entities":[[0,13,"EQUIPMENT"],[15,25,"TYPE"],[27,30,"FUEL_TYPE"],[33,40,"CAPACITY"],[42,56,"POWER"],[59,66,"FLOWRATE"]]}],["Water Heaters, Commercial, Oil - 411 gal, 1250 MBH input, 1200 GPH\r",{"entities":[[0,13,"EQUIPMENT"],[15,25,"TYPE"],[27,30,"FUEL_TYPE"],[33,40,"CAPACITY"],[42,56,"POWER"],[58,66,"FLOWRATE"]]}],["Water Heaters, Residential, Electric\r",{"entities":[[0,13,"EQUIPMENT"],[15,26,"TYPE"],[28,36,"FUEL_TYPE"]]}],["Water Heaters, Residential, Gas\r",{"entities":[[0,13,"EQUIPMENT"],[15,26,"TYPE"],[28,31,"FUEL_TYPE"]]}],["Water Heaters, Residential, Oil\r",{"entities":[[0,13,"EQUIPMENT"],[15,26,"TYPE"],[28,31,"FUEL_TYPE"]]}],["Sanitary Waste Separator\r",{"entities":[[0,24,"EQUIPMENT"]]}],["Sanitary Waste Separator - 2\" size\r",{"entities":[[0,24,"EQUIPMENT"],[27,29,"SIZE"]]}],["Sanitary Waste Separator - 3\" size\r",{"entities":[[0,24,"EQUIPMENT"],[27,29,"SIZE"]]}],["Sanitary Waste Separator - 4\" size\r",{"entities":[[0,24,"EQUIPMENT"],[27,29,"SIZE"]]}],["Sanitary Waste Separator - 6\" size",{"entities":[[0,24,"EQUIPMENT"],[27,29,"SIZE"]]}],["Bathtub\r",{"entities":[]}],["Black / Galvanized Steel  <1\" Pipe\r",{"entities":[]}],["Black / Galvanized Steel  1\"-2\" Pipe\r",{"entities":[]}],["Black / Galvanized Steel  2\"-4\" Pipe\r",{"entities":[]}],["Black / Galvanized Steel  4\"-6\" Pipe\r",{"entities":[]}],["Black / Galvanized Steel >6\" Pipe\r",{"entities":[]}],["Combo (Eye Wash and Shower)\r",{"entities":[]}],["Combo Unit (Shower / Tub)\r",{"entities":[]}],["Copper  <1\" Pipe\r",{"entities":[]}],["Copper  1\"-2\" Pipe\r",{"entities":[]}],["Copper  2\"-4\" Pipe\r",{"entities":[]}],["CPVC  <1\" Pipe\r",{"entities":[]}],["CPVC  1\"-2\" Pipe\r",{"entities":[]}],["CPVC  2\"-4\" Pipe\r",{"entities":[]}],["Drinking Fountain\r",{"entities":[]}],["Ductile Iron  4\" Pipe\r",{"entities":[]}],["Ductile Iron  6\" Pipe\r",{"entities":[]}],["Emergency Eye Wash\r",{"entities":[]}],["Emergency Shower\r",{"entities":[]}],["General\r",{"entities":[]}],["Group Wash Fountain\r",{"entities":[]}],["Hose Bib\r",{"entities":[]}],["Kitchen Faucets\r",{"entities":[]}],["Kitchen Sink\r",{"entities":[]}],["Laboratory Sink\r",{"entities":[]}],["Laundry Sink\r",{"entities":[]}],["Mop Sink\r",{"entities":[]}],["Other\r",{"entities":[]}],["PVC  2\"-4\" Pipe\r",{"entities":[]}],["PVC  4\"-6\" Pipe\r",{"entities":[]}],["PVC < 2\" Pipe\r",{"entities":[]}],["Service Sink\r",{"entities":[]}],["Shower\r",{"entities":[]}],["Stainless\r",{"entities":[]}],["Stainless Steel Combo Unit (WC/Sink)\r",{"entities":[]}],["Sump\r",{"entities":[]}],["Sump Pump - Duplex\r",{"entities":[]}],["Sump Pump - Submersible\r",{"entities":[]}],["Trench Drain\r",{"entities":[]}],["Unknown\r",{"entities":[]}],["Washer / Dryer Hookup\r",{"entities":[]}],["Washer/Dryer Faucets\r",{"entities":[]}],["Water Cooler\r",{"entities":[]}],["Water Fountain With Bottle Filler\r",{"entities":[]}],["Water Softener\r",{"entities":[]}],["Water Treatment Equipment\r",{"entities":[]}],["Water Treatment Equipment - Chemical Treatment\r",{"entities":[]}],["Water Treatment Equipment - Deionization Station\r",{"entities":[]}],["Water Treatment Equipment - Ultraviolet Treatment\r",{"entities":[]}],["Water Treatment Equipment - Wastewater Filtration for WashRack Equipment\r",{"entities":[]}]]}